rubino/__init__.py
rubino-1.0.0.dist-info/METADATA
rubino-1.0.0.dist-info/WHEEL
rubino-1.0.0.dist-info/top_level.txt
rubino-1.0.0.dist-info/RECORD
